{
    "DisasterFloodingID": "98468128-d432-413c-a90b-452d3005fb92",
    "Time": "2025-03-06T06:10:00",
    "CategoryCode": 1,
    "SourceCode": 7,
    "CaseNo": "仁美市場",
    "OperatorName": "第四河川分署",
    "TownCode": "1000703",
    "Situation": "目前感測值 8公分",
    "Location": "山犁里仁美市場230號",
    "Point": {
        "Latitude": 24.109,
        "Longitude": 120.497
    },
    "Depth": 10,
    "Treatment": null,
    "IsReceded": true,
    "RecededDate": "2025-03-06T07:33:40",
    "Type": 1,
    "Photo": null
}