{
    "DisasterFloodingID": "8d19b704-0c03-41ee-a02e-49c7e300fcc9",
    "Time": "2024-10-03T15:32:00",
    "CategoryCode": 2,
    "SourceCode": 4,
    "CaseNo": "072024058233437",
    "OperatorName": "第十河川分署",
    "TownCode": "1001706",
    "Situation": "2024\/10\/03 15:32:17 - 積水面積約4×15平方公尺積水深度約15cm",
    "Location": "基隆市安樂區興寮里民活動中心對向車道",
    "Point": {
        "Latitude": 25.1210152171812,
        "Longitude": 121.720973559336
    },
    "Depth": 15,
    "Treatment": "EMIC資訊：待處理.未結案.未退水",
    "IsReceded": true,
    "RecededDate": "2024-10-03T18:00:00",
    "Type": 15,
    "Photo": []
}