{
    "DisasterFloodingID": "cd5eaa93-6171-4092-a4bb-af3246b13fb8",
    "Time": "2024-10-24T17:49:00",
    "CategoryCode": 2,
    "SourceCode": 4,
    "CaseNo": "042024058393598",
    "OperatorName": "第十河川分署",
    "TownCode": "1001702",
    "Situation": "沿線邊坡排水溝石頭阻塞影響排水",
    "Location": "基隆市七堵區華新二路97巷",
    "Point": {
        "Latitude": 25.117265,
        "Longitude": 121.658355
    },
    "Depth": 0,
    "Treatment": "EMIC資訊：待處理.未結案.未退水",
    "IsReceded": false,
    "RecededDate": null,
    "Type": 1,
    "Photo": []
}