{
    "type": "FeatureCollection",
    "features": [
        {
            "type": "Feature",
            "properties": {
                "authority": "Operator-414",
                "stationID": "e600405a-ee81-455e-a057-a10bc3ff0284",
                "stationName": "CYC102朴子市新寮里新寮社區",
                "address": "新寮里新寮社區",
                "sensorType": "壓力式",
                "unitOfMeasurement": "cm",
                "result": 3.2,
                "phenomenonTime": "2026-07-07T15:12:21+08:00",
                "transferTime": "2026-07-07T15:15:10+08:00",
                "toBeConfirm": true,
                "isCulvert": false,
                "cityCode": "10010",
                "townCode": "1001002",
                "dataSource": "IoT-Sensor"
            },
            "geometry": {
                "type": "Point",
                "coordinates": [
                    120.24125,
                    23.45013
                ]
            }
        },
        {
            "type": "Feature",
            "properties": {
                "authority": "Operator-414",
                "stationID": "65674105-a760-449c-8028-ac65f101fbc2",
                "stationName": "CYC124竹崎鄉鹿滿村鹿滿社區",
                "address": "鹿滿村鹿滿社區",
                "sensorType": "壓力式",
                "unitOfMeasurement": "cm",
                "result": 3.1,
                "phenomenonTime": "2026-07-07T15:12:30+08:00",
                "transferTime": "2026-07-07T15:15:44+08:00",
                "toBeConfirm": true,
                "isCulvert": false,
                "cityCode": "10010",
                "townCode": "1001014",
                "dataSource": "IoT-Sensor"
            },
            "geometry": {
                "type": "Point",
                "coordinates": [
                    120.540438,
                    23.509172
                ]
            }
        },
        {
            "type": "Feature",
            "properties": {
                "authority": "Operator-411",
                "stationID": "3fa6ca0f-c9d9-438f-aa2e-f8ea0645ee30",
                "stationName": "舊社村1",
                "address": "彰南路六段131號",
                "sensorType": "壓力式",
                "unitOfMeasurement": "cm",
                "result": 4.7,
                "phenomenonTime": "2026-07-07T15:06:00+08:00",
                "transferTime": "2026-07-07T15:15:44+08:00",
                "toBeConfirm": true,
                "isCulvert": false,
                "cityCode": "10007",
                "townCode": "1000701",
                "dataSource": "IoT-Sensor"
            },
            "geometry": {
                "type": "Point",
                "coordinates": [
                    120.6198664,
                    24.0543356
                ]
            }
        },
        {
            "type": "Feature",
            "properties": {
                "authority": "Operator-414",
                "stationID": "2d45b414-d204-4a44-bd01-711356ce7bfe",
                "stationName": "CYC104東石鄉鰲鼓村四股社區",
                "address": "鰲鼓村四股社區",
                "sensorType": "壓力式",
                "unitOfMeasurement": "cm",
                "result": 3.1,
                "phenomenonTime": "2026-07-07T15:13:29+08:00",
                "transferTime": "2026-07-07T15:15:58+08:00",
                "toBeConfirm": true,
                "isCulvert": false,
                "cityCode": "10010",
                "townCode": "1001009",
                "dataSource": "IoT-Sensor"
            },
            "geometry": {
                "type": "Point",
                "coordinates": [
                    120.160994,
                    23.508853
                ]
            }
        },
        {
            "type": "Feature",
            "properties": {
                "authority": "Operator-414",
                "stationID": "f798b1c5-f4ab-4431-9de7-04c1660f666b",
                "stationName": "民雄鄉中樂村民雄",
                "address": "保安宮騎虎王廟旁",
                "sensorType": "壓力式",
                "unitOfMeasurement": "cm",
                "result": 3.3,
                "phenomenonTime": "2026-07-07T15:13:53+08:00",
                "transferTime": "2026-07-07T15:15:49+08:00",
                "toBeConfirm": true,
                "isCulvert": false,
                "cityCode": "10010",
                "townCode": "1001005",
                "dataSource": "IoT-Sensor"
            },
            "geometry": {
                "type": "Point",
                "coordinates": [
                    120.42971,
                    23.5529
                ]
            }
        },
        {
            "type": "Feature",
            "properties": {
                "authority": "Operator-414",
                "stationID": "06eec8b7-512e-4c82-950d-95712d0f3519",
                "stationName": "布袋鎮振寮里後壁寮B站",
                "address": "振寮里後壁寮2號旁",
                "sensorType": "壓力式",
                "unitOfMeasurement": "cm",
                "result": 3.1,
                "phenomenonTime": "2026-07-07T15:14:33+08:00",
                "transferTime": "2026-07-07T15:16:03+08:00",
                "toBeConfirm": true,
                "isCulvert": false,
                "cityCode": "10010",
                "townCode": "1001003",
                "dataSource": "IoT-Sensor"
            },
            "geometry": {
                "type": "Point",
                "coordinates": [
                    120.18217,
                    23.38423
                ]
            }
        },
        {
            "type": "Feature",
            "properties": {
                "authority": "Operator-414",
                "stationID": "45b5ecba-f6dc-47f5-95fa-5de729beb5c9",
                "stationName": "朴子市平和里",
                "address": "文明南路1號",
                "sensorType": "壓力式",
                "unitOfMeasurement": "cm",
                "result": 3.1,
                "phenomenonTime": "2026-07-07T15:13:08+08:00",
                "transferTime": "2026-07-07T15:16:06+08:00",
                "toBeConfirm": true,
                "isCulvert": false,
                "cityCode": "10010",
                "townCode": "1001002",
                "dataSource": "IoT-Sensor"
            },
            "geometry": {
                "type": "Point",
                "coordinates": [
                    120.24919,
                    23.46103
                ]
            }
        },
        {
            "type": "Feature",
            "properties": {
                "authority": "Operator-403",
                "stationID": "a0ae74f8-8a8b-4262-86ca-8520f9a3159c",
                "stationName": "板橋區龍興街73巷2號",
                "address": "龍興街73巷2號",
                "sensorType": "壓力式",
                "unitOfMeasurement": "cm",
                "result": 4,
                "phenomenonTime": "2026-07-07T14:59:00+08:00",
                "transferTime": "2026-07-07T15:05:56+08:00",
                "toBeConfirm": false,
                "isCulvert": false,
                "cityCode": "65",
                "townCode": "6500100",
                "dataSource": "IoT-Sensor"
            },
            "geometry": {
                "type": "Point",
                "coordinates": [
                    121.443912,
                    25.002205
                ]
            }
        },
        {
            "type": "Feature",
            "properties": {
                "authority": "Operator-414",
                "stationID": "f5d3dc0d-e075-4e58-b5d6-2993f17c4e20",
                "stationName": "CYC120太保市安仁里橋子頭社區",
                "address": "安仁里橋子頭社區",
                "sensorType": "壓力式",
                "unitOfMeasurement": "cm",
                "result": 3,
                "phenomenonTime": "2026-07-07T15:14:31+08:00",
                "transferTime": "2026-07-07T15:16:07+08:00",
                "toBeConfirm": true,
                "isCulvert": false,
                "cityCode": "10010",
                "townCode": "1001001",
                "dataSource": "IoT-Sensor"
            },
            "geometry": {
                "type": "Point",
                "coordinates": [
                    120.315505,
                    23.449703
                ]
            }
        },
        {
            "type": "Feature",
            "properties": {
                "authority": "Operator-414",
                "stationID": "f6369228-4640-4475-929f-646077afa7aa",
                "stationName": "CYC146鹿草鄉鹿草村鹿草市區",
                "address": "鹿草村鹿草市區",
                "sensorType": "壓力式",
                "unitOfMeasurement": "cm",
                "result": 3,
                "phenomenonTime": "2026-07-07T15:12:28+08:00",
                "transferTime": "2026-07-07T15:16:07+08:00",
                "toBeConfirm": true,
                "isCulvert": false,
                "cityCode": "10010",
                "townCode": "1001011",
                "dataSource": "IoT-Sensor"
            },
            "geometry": {
                "type": "Point",
                "coordinates": [
                    120.3101796,
                    23.4124308
                ]
            }
        },
        {
            "type": "Feature",
            "properties": {
                "authority": "Operator-414",
                "stationID": "4de5fee4-de80-4268-94fc-e451c427e055",
                "stationName": "CYC101朴子市永和里福山社區",
                "address": "永和里福山社區",
                "sensorType": "壓力式",
                "unitOfMeasurement": "cm",
                "result": 3,
                "phenomenonTime": "2026-07-07T15:12:33+08:00",
                "transferTime": "2026-07-07T15:16:07+08:00",
                "toBeConfirm": true,
                "isCulvert": false,
                "cityCode": "10010",
                "townCode": "1001002",
                "dataSource": "IoT-Sensor"
            },
            "geometry": {
                "type": "Point",
                "coordinates": [
                    120.229215,
                    23.45231
                ]
            }
        },
        {
            "type": "Feature",
            "properties": {
                "authority": "Operator-414",
                "stationID": "a89f97e3-374e-48ca-9843-dbf7da636019",
                "stationName": "CYC156義竹北華村南安溪寮",
                "address": "北華村北華",
                "sensorType": "壓力式",
                "unitOfMeasurement": "cm",
                "result": 3,
                "phenomenonTime": "2026-07-07T15:12:02+08:00",
                "transferTime": "2026-07-07T15:16:07+08:00",
                "toBeConfirm": true,
                "isCulvert": false,
                "cityCode": "10010",
                "townCode": "1001010",
                "dataSource": "IoT-Sensor"
            },
            "geometry": {
                "type": "Point",
                "coordinates": [
                    120.19554,
                    23.34224
                ]
            }
        },
        {
            "type": "Feature",
            "properties": {
                "authority": "Operator-414",
                "stationID": "cbe17d3e-32b9-43ea-bc5f-dd9032404f78",
                "stationName": "CYC174鹿草三角村1",
                "address": "三角村1",
                "sensorType": "壓力式",
                "unitOfMeasurement": "cm",
                "result": 1.8,
                "phenomenonTime": "2026-07-07T15:12:02+08:00",
                "transferTime": "2026-07-07T15:16:07+08:00",
                "toBeConfirm": true,
                "isCulvert": false,
                "cityCode": "10010",
                "townCode": "1001011",
                "dataSource": "IoT-Sensor"
            },
            "geometry": {
                "type": "Point",
                "coordinates": [
                    120.33976,
                    23.399589
                ]
            }
        },
        {
            "type": "Feature",
            "properties": {
                "authority": "Operator-414",
                "stationID": "27a44fa1-69d6-42da-9875-8b47b09a6046",
                "stationName": "CYC203朴子竹村里藍天社區",
                "address": "竹村里藍天社區",
                "sensorType": "壓力式",
                "unitOfMeasurement": "cm",
                "result": 3.2,
                "phenomenonTime": "2026-07-07T15:12:02+08:00",
                "transferTime": "2026-07-07T15:16:08+08:00",
                "toBeConfirm": true,
                "isCulvert": false,
                "cityCode": "10010",
                "townCode": "1001002",
                "dataSource": "IoT-Sensor"
            },
            "geometry": {
                "type": "Point",
                "coordinates": [
                    120.2474481,
                    23.4436937
                ]
            }
        },
        {
            "type": "Feature",
            "properties": {
                "authority": "Operator-414",
                "stationID": "74fab0d9-39be-43c9-9117-afb73b3199c7",
                "stationName": "CYC217布袋鎮菜舖里菜鋪社區活動中心",
                "address": "布袋鎮菜舖里菜鋪社區活動中心",
                "sensorType": "壓力式",
                "unitOfMeasurement": "cm",
                "result": 3,
                "phenomenonTime": "2026-07-07T15:12:02+08:00",
                "transferTime": "2026-07-07T15:16:06+08:00",
                "toBeConfirm": true,
                "isCulvert": false,
                "cityCode": "10010",
                "townCode": "1001003",
                "dataSource": "IoT-Sensor"
            },
            "geometry": {
                "type": "Point",
                "coordinates": [
                    120.21557,
                    23.3858
                ]
            }
        },
        {
            "type": "Feature",
            "properties": {
                "authority": "Operator-414",
                "stationID": "ea9f277e-0dbe-4404-95db-18b75e07a748",
                "stationName": "CYC231太保梅埔里梅子厝保福宮",
                "address": "太保梅埔里梅子厝保福宮",
                "sensorType": "壓力式",
                "unitOfMeasurement": "cm",
                "result": 3.1,
                "phenomenonTime": "2026-07-07T15:12:02+08:00",
                "transferTime": "2026-07-07T15:16:06+08:00",
                "toBeConfirm": true,
                "isCulvert": false,
                "cityCode": "10010",
                "townCode": "1001001",
                "dataSource": "IoT-Sensor"
            },
            "geometry": {
                "type": "Point",
                "coordinates": [
                    120.34123,
                    23.439647
                ]
            }
        },
        {
            "type": "Feature",
            "properties": {
                "authority": "Operator-414",
                "stationID": "57790337-1e84-4b78-978b-5e2dc5db85a5",
                "stationName": "CYC240六腳溪厝村溪墘厝",
                "address": "溪厝村溪墘厝",
                "sensorType": "壓力式",
                "unitOfMeasurement": "cm",
                "result": 3,
                "phenomenonTime": "2026-07-07T15:12:02+08:00",
                "transferTime": "2026-07-07T15:16:06+08:00",
                "toBeConfirm": true,
                "isCulvert": false,
                "cityCode": "10010",
                "townCode": "1001008",
                "dataSource": "IoT-Sensor"
            },
            "geometry": {
                "type": "Point",
                "coordinates": [
                    120.26639,
                    23.495929
                ]
            }
        },
        {
            "type": "Feature",
            "properties": {
                "authority": "Operator-425",
                "stationID": "8777e147-1ad2-4029-8bdb-14b5cafca73e",
                "stationName": "保安殿周邊",
                "address": "保安殿周邊",
                "sensorType": "壓力式",
                "unitOfMeasurement": "cm",
                "result": 1,
                "phenomenonTime": "2026-07-07T15:10:00+08:00",
                "transferTime": "2026-07-07T15:16:08+08:00",
                "toBeConfirm": true,
                "isCulvert": false,
                "cityCode": "9020",
                "townCode": "902004",
                "dataSource": "IoT-Sensor"
            },
            "geometry": {
                "type": "Point",
                "coordinates": [
                    118.32465,
                    24.46278
                ]
            }
        }
    ]
}