{
    "type": "FeatureCollection",
    "features": [
        {
            "type": "Feature",
            "properties": {
                "authority": "第六河川分署",
                "stationID": "49122391-f6bd-420b-a30b-01fd50291976",
                "stationName": "042024058576057",
                "unitOfMeasurement": "cm",
                "result": 0,
                "phenomenonTime": "2024-11-16T03:19:00"
            },
            "geometry": {
                "type": "Point",
                "coordinates": [
                    120.29324,
                    22.794324
                ]
            }
        },
        {
            "type": "Feature",
            "properties": {
                "authority": "第六河川分署",
                "stationID": "ea19ec4e-92df-4991-a48f-ea55c8dd9d91",
                "stationName": "漁光路81號以南後抽水站(編號146)",
                "unitOfMeasurement": "cm",
                "result": 25,
                "phenomenonTime": "2024-11-16T03:39:03"
            },
            "geometry": {
                "type": "Point",
                "coordinates": [
                    120.162823,
                    22.973927
                ]
            }
        }
    ]
}