{
    "type": "FeatureCollection",
    "features": [
        {
            "type": "Feature",
            "properties": {
                "authority": "第二河川分署",
                "stationID": "681afc52-a707-4649-9dae-180af781d0e8",
                "stationName": "文化二路138號",
                "unitOfMeasurement": "cm",
                "result": 21,
                "phenomenonTime": "2025-05-29T13:55:00"
            },
            "geometry": {
                "type": "Point",
                "coordinates": [
                    121.370358,
                    25.053535
                ]
            }
        }
    ]
}