{
    "DisasterFloodingID": "7f26528b-7d9b-4338-9601-0b6629eb9887",
    "Time": "2025-08-02T05:42:00",
    "CategoryCode": 1,
    "SourceCode": 7,
    "CaseNo": "頂安里長溪路一段408-1號旁(編號243)",
    "OperatorName": "第六河川分署",
    "TownCode": "6703500",
    "Situation": "頂安里長溪路一段408-1號旁(編號243)",
    "Location": "頂安里長溪路一段408-1號旁",
    "Point": {
        "Latitude": 23.040072,
        "Longitude": 120.205729
    },
    "Depth": 12.8,
    "Treatment": "頂安里長溪路一段408-1號旁(編號243)",
    "IsReceded": true,
    "RecededDate": "2025-08-02T06:30:00",
    "Type": 1,
    "Photo": [
        null
    ]
}